pypckage/Pypckage.py
pypckage/__init__.py
pypckage-1.0.12.dist-info/LICENSE
pypckage-1.0.12.dist-info/METADATA
pypckage-1.0.12.dist-info/WHEEL
pypckage-1.0.12.dist-info/entry_points.txt
pypckage-1.0.12.dist-info/top_level.txt
pypckage-1.0.12.dist-info/RECORD
