Metadata-Version: 2.1
Name: pypckage
Version: 1.0.12
Summary: Pypckage is a tool to facilitate the configuration of a python package.
Home-page: https://github.com/LixNew2/Pypckage
Author: LixNew
Author-email: lixnew2@gmail.com
Classifier: Programming Language :: Python :: 3
Classifier: License :: OSI Approved :: MIT License
Classifier: Operating System :: OS Independent
Requires-Python: >=3.6
License-File: LICENSE
Requires-Dist: psutil
